[
  {
    "variation": "default-slice",
    "name": "Default slice",
    "slice_type": "blog",
    "items": [
      {
        "title": "brand real-time metrics",
        "link": {
          "link_type": "Web",
          "url": "https://slicemachine.dev"
        },
        "image": {
          "dimensions": {
            "width": 900,
            "height": 500
          },
          "alt": "Placeholder image",
          "copyright": null,
          "url": "https://images.unsplash.com/photo-1587653915936-5623ea0b949a?w=900&h=500&fit=crop"
        },
        "body": [
          {
            "type": "paragraph",
            "text": "Velit aliqua velit deserunt do qui occaecat velit tempor deserunt sunt commodo consectetur laboris sint velit. Et eiusmod dolore do Lorem.",
            "spans": []
          }
        ],
        "featured": false
      },
      {
        "title": "integrate efficient infomediaries",
        "link": {
          "link_type": "Web",
          "url": "https://slicemachine.dev"
        },
        "image": {
          "dimensions": {
            "width": 900,
            "height": 500
          },
          "alt": "Placeholder image",
          "copyright": null,
          "url": "https://images.unsplash.com/photo-1589321578146-4c1ba445cc88?w=900&h=500&fit=crop"
        },
        "body": [
          {
            "type": "paragraph",
            "text": "Aliqua incididunt irure ea. Et enim laborum proident in ad dolor incididunt culpa.",
            "spans": []
          }
        ],
        "featured": true
      },
      {
        "title": "whiteboard bleeding-edge action-items",
        "link": {
          "link_type": "Web",
          "url": "https://prismic.io"
        },
        "image": {
          "dimensions": {
            "width": 900,
            "height": 500
          },
          "alt": "Placeholder image",
          "copyright": null,
          "url": "https://images.unsplash.com/photo-1547394765-185e1e68f34e?w=900&h=500&fit=crop"
        },
        "body": [
          {
            "type": "paragraph",
            "text": "Excepteur incididunt nostrud sit non tempor ea deserunt laborum eiusmod. Amet pariatur eu dolor est aute pariatur Lorem dolore eiusmod sunt reprehenderit minim culpa. Mollit reprehenderit do do exercitation labore anim incididunt.",
            "spans": []
          }
        ],
        "featured": true
      },
      {
        "title": "deliver sticky bandwidth",
        "link": {
          "link_type": "Web",
          "url": "https://prismic.io"
        },
        "image": {
          "dimensions": {
            "width": 900,
            "height": 500
          },
          "alt": "Placeholder image",
          "copyright": null,
          "url": "https://images.unsplash.com/photo-1579931794097-0ad001e51edb?w=900&h=500&fit=crop"
        },
        "body": [
          {
            "type": "paragraph",
            "text": "Laborum tempor pariatur velit culpa fugiat sint magna. Magna esse dolor ut sunt deserunt duis sint voluptate velit aute.",
            "spans": []
          }
        ],
        "featured": false
      }
    ],
    "primary": {}
  }
]